candphy/__init__.py
candphy/logs/__init__.py
candphy/logs/_log_.py
candphy/waves/__init__.py
candphy/waves/gwaves.py
candphy/waves/plot.py
candphy/waves/sdr.py
candphy-0.0.2021.dist-info/LICENSE
candphy-0.0.2021.dist-info/METADATA
candphy-0.0.2021.dist-info/WHEEL
candphy-0.0.2021.dist-info/top_level.txt
candphy-0.0.2021.dist-info/RECORD
