Metadata-Version: 2.1
Name: candphy
Version: 0.0.2021
Summary: Library for works in the physical projects
Home-page: https://github.com/perseu912/candphy
Author: Reinan Br
Author-email: slimchatuba@gmail.com
License: MIT License
Keywords: covid-19 covid api data science
License-File: LICENSE
Requires-Dist: openpyxl
Requires-Dist: pyrtlsdr
Requires-Dist: bs4
Requires-Dist: requests
Requires-Dist: soundfile
Requires-Dist: pandas
Requires-Dist: h5py
Requires-Dist: astropy
Requires-Dist: scipy
Requires-Dist: toddy
Requires-Dist: numpy
Requires-Dist: matplotlib
Requires-Dist: pillow
Requires-Dist: qutip
